[{"code": "A", "regionLabel": "Oblast Burgas", "countryLabel": "Bulgarien"}, {"code": "A", "regionLabel": "Malko Tarnowo", "countryLabel": "Bulgarien"}, {"code": "AA", "regionLabel": "Primorsko", "countryLabel": "Bulgarien"}, {"code": "B", "regionLabel": "Slanchevo", "countryLabel": "Bulgarien"}, {"code": "B", "regionLabel": "Oblast Warna", "countryLabel": "Bulgarien"}, {"code": "BG", "regionLabel": "Bulgarien", "countryLabel": "Bulgarien"}, {"code": "BH", "regionLabel": "Oblast Widin", "countryLabel": "Bulgarien"}, {"code": "BT", "regionLabel": "Oblast Weliko Tarnowo", "countryLabel": "Bulgarien"}, {"code": "C", "regionLabel": "Sofia", "countryLabel": "Bulgarien"}, {"code": "CA", "regionLabel": "Sofia", "countryLabel": "Bulgarien"}, {"code": "CB", "regionLabel": "Sofia", "countryLabel": "Bulgarien"}, {"code": "CB", "regionLabel": "Oblast Sofia-Stadt", "countryLabel": "Bulgarien"}, {"code": "CC", "regionLabel": "Oblast Silistra", "countryLabel": "Bulgarien"}, {"code": "CO", "regionLabel": "Prawez", "countryLabel": "Bulgarien"}, {"code": "CO", "regionLabel": "Botewgrad", "countryLabel": "Bulgarien"}, {"code": "CO", "regionLabel": "Chavdar", "countryLabel": "Bulgarien"}, {"code": "E", "regionLabel": "Petritsch", "countryLabel": "Bulgarien"}, {"code": "E", "regionLabel": "Oblast Blagoewgrad", "countryLabel": "Bulgarien"}, {"code": "EB", "regionLabel": "Oblast Gabrowo", "countryLabel": "Bulgarien"}, {"code": "EH", "regionLabel": "Oblast Plewen", "countryLabel": "Bulgarien"}, {"code": "KH", "regionLabel": "Oblast Kjustendil", "countryLabel": "Bulgarien"}, {"code": "M", "regionLabel": "Oblast Montana", "countryLabel": "Bulgarien"}, {"code": "M", "regionLabel": "Yakimovo", "countryLabel": "Bulgarien"}, {"code": "M", "regionLabel": "Berkovitsa", "countryLabel": "Bulgarien"}, {"code": "OB", "regionLabel": "Oblast Lowetsch", "countryLabel": "Bulgarien"}, {"code": "PA", "regionLabel": "Septemwri", "countryLabel": "Bulgarien"}, {"code": "PA", "regionLabel": "Septemvri", "countryLabel": "Bulgarien"}, {"code": "PA", "regionLabel": "Slavovitsa", "countryLabel": "Bulgarien"}, {"code": "PA", "regionLabel": "Lozen", "countryLabel": "Bulgarien"}, {"code": "PA", "regionLabel": "Karabunar", "countryLabel": "Bulgarien"}, {"code": "PA", "regionLabel": "Sveti Konstantin", "countryLabel": "Bulgarien"}, {"code": "X", "regionLabel": "Oblast Chaskowo", "countryLabel": "Bulgarien"}, {"code": "А", "regionLabel": "Burgas", "countryLabel": "Bulgarien"}, {"code": "ВР", "regionLabel": "Oblast Wraza", "countryLabel": "Bulgarien"}, {"code": "ВТ", "regionLabel": "Weliko Tarnowo", "countryLabel": "Bulgarien"}, {"code": "ВТ", "regionLabel": "Swischtow", "countryLabel": "Bulgarien"}, {"code": "Е", "regionLabel": "Blagoewgrad", "countryLabel": "Bulgarien"}, {"code": "К", "regionLabel": "Krumovgrad", "countryLabel": "Bulgarien"}, {"code": "К", "regionLabel": "Oblast Kardschali", "countryLabel": "Bulgarien"}, {"code": "Н", "regionLabel": "Oblast Schumen", "countryLabel": "Bulgarien"}, {"code": "Р", "regionLabel": "Oblast Russe", "countryLabel": "Bulgarien"}, {"code": "РА", "regionLabel": "Pasardschik", "countryLabel": "Bulgarien"}, {"code": "РА", "regionLabel": "Oblast Pasardschik", "countryLabel": "Bulgarien"}, {"code": "РВ", "regionLabel": "Oblast Plowdiw", "countryLabel": "Bulgarien"}, {"code": "РВ (П)", "regionLabel": "Plowdiw", "countryLabel": "Bulgarien"}, {"code": "РК", "regionLabel": "Oblast Pernik", "countryLabel": "Bulgarien"}, {"code": "РР", "regionLabel": "Oblast Rasgrad", "countryLabel": "Bulgarien"}, {"code": "С", "regionLabel": "Oblast Sofia-Stadt", "countryLabel": "Bulgarien"}, {"code": "СА", "regionLabel": "Oblast Sofia-Stadt", "countryLabel": "Bulgarien"}, {"code": "СМ", "regionLabel": "Oblast Smoljan", "countryLabel": "Bulgarien"}, {"code": "СН", "regionLabel": "Oblast Sliwen", "countryLabel": "Bulgarien"}, {"code": "СО", "regionLabel": "Oblast Sofia", "countryLabel": "Bulgarien"}, {"code": "СТ", "regionLabel": "Stara Sagora", "countryLabel": "Bulgarien"}, {"code": "СТ", "regionLabel": "Oblast Stara Sagora", "countryLabel": "Bulgarien"}, {"code": "Т", "regionLabel": "Oblast Targowischte", "countryLabel": "Bulgarien"}, {"code": "ТХ", "regionLabel": "Dobritsch", "countryLabel": "Bulgarien"}, {"code": "ТХ", "regionLabel": "Oblast Dobritsch", "countryLabel": "Bulgarien"}, {"code": "ТХ", "regionLabel": "Rusalka", "countryLabel": "Bulgarien"}, {"code": "У", "regionLabel": "Oblast Jambol", "countryLabel": "Bulgarien"}, {"code": "Х", "regionLabel": "Lyubimets", "countryLabel": "Bulgarien"}, {"code": "http://www.wikidata.org/.well-known/genid/4e19c77cdda68a5efa80f71cee056e7b", "regionLabel": "Perlacher Forst", "countryLabel": "Deutschland"}, {"code": "http://www.wikidata.org/.well-known/genid/a9bba7d536a9de9c2c7d17d7804d23e2", "regionLabel": "Grünwalder Forst", "countryLabel": "Deutschland"}, {"code": "http://www.wikidata.org/.well-known/genid/e3d37aa01576f3c2192e98cf8a4fed6c", "regionLabel": "Forstenrieder Park", "countryLabel": "Deutschland"}, {"code": "A", "regionLabel": "Augsburg", "countryLabel": "Deutschland"}, {"code": "A", "regionLabel": "Landkreis Augsburg", "countryLabel": "Deutschland"}, {"code": "A", "regionLabel": "Mickhausen", "countryLabel": "Deutschland"}, {"code": "A", "regionLabel": "Walkertshofen", "countryLabel": "Deutschland"}, {"code": "A", "regionLabel": "Zusmarshausen", "countryLabel": "Deutschland"}, {"code": "A", "regionLabel": "Meitingen", "countryLabel": "Deutschland"}, {"code": "A", "regionLabel": "Bobingen", "countryLabel": "Deutschland"}, {"code": "A", "regionLabel": "Ustersbach", "countryLabel": "Deutschland"}, {"code": "A", "regionLabel": "Thierhaupten", "countryLabel": "Deutschland"}, {"code": "A", "regionLabel": "Adelsried", "countryLabel": "Deutschland"}, {"code": "A", "regionLabel": "Mittelneufnach", "countryLabel": "Deutschland"}, {"code": "A", "regionLabel": "Wehringen", "countryLabel": "Deutschland"}, {"code": "A", "regionLabel": "Altenmünster", "countryLabel": "Deutschland"}, {"code": "A", "regionLabel": "Gersthofen", "countryLabel": "Deutschland"}, {"code": "A", "regionLabel": "Ellgau", "countryLabel": "Deutschland"}, {"code": "A", "regionLabel": "Aystetten", "countryLabel": "Deutschland"}, {"code": "A", "regionLabel": "Untermeitingen", "countryLabel": "Deutschland"}, {"code": "A", "regionLabel": "Stadtbergen", "countryLabel": "Deutschland"}, {"code": "A", "regionLabel": "Emersacker", "countryLabel": "Deutschland"}, {"code": "A", "regionLabel": "Dinkelscherben", "countryLabel": "Deutschland"}, {"code": "A", "regionLabel": "Fischach", "countryLabel": "Deutschland"}, {"code": "A", "regionLabel": "Nordendorf", "countryLabel": "Deutschland"}, {"code": "A", "regionLabel": "Oberottmarshausen", "countryLabel": "Deutschland"}, {"code": "A", "regionLabel": "Allmannshofen", "countryLabel": "Deutschland"}, {"code": "A", "regionLabel": "Klosterlechfeld", "countryLabel": "Deutschland"}, {"code": "A", "regionLabel": "Diedorf", "countryLabel": "Deutschland"}, {"code": "A", "regionLabel": "Westendorf", "countryLabel": "Deutschland"}, {"code": "A", "regionLabel": "Königsbrunn", "countryLabel": "Deutschland"}, {"code": "A", "regionLabel": "Welden", "countryLabel": "Deutschland"}, {"code": "A", "regionLabel": "Gessertshausen", "countryLabel": "Deutschland"}, {"code": "A", "regionLabel": "Kleinaitingen", "countryLabel": "Deutschland"}, {"code": "A", "regionLabel": "Heretsried", "countryLabel": "Deutschland"}, {"code": "A", "regionLabel": "Scherstetten", "countryLabel": "Deutschland"}, {"code": "A", "regionLabel": "Langenneufnach", "countryLabel": "Deutschland"}, {"code": "A", "regionLabel": "Hiltenfingen", "countryLabel": "Deutschland"}, {"code": "A", "regionLabel": "Großaitingen", "countryLabel": "Deutschland"}, {"code": "A", "regionLabel": "Graben", "countryLabel": "Deutschland"}, {"code": "A", "regionLabel": "Langerringen", "countryLabel": "Deutschland"}, {"code": "A", "regionLabel": "Kutzenhausen", "countryLabel": "Deutschland"}, {"code": "A", "regionLabel": "Biberbach", "countryLabel": "Deutschland"}, {"code": "A", "regionLabel": "Kühlenthal", "countryLabel": "Deutschland"}, {"code": "A", "regionLabel": "Gablingen", "countryLabel": "Deutschland"}, {"code": "A", "regionLabel": "Horgau", "countryLabel": "Deutschland"}, {"code": "A", "regionLabel": "Bonstetten", "countryLabel": "Deutschland"}, {"code": "A", "regionLabel": "Langweid am Lech", "countryLabel": "Deutschland"}, {"code": "A", "regionLabel": "Ehingen", "countryLabel": "Deutschland"}, {"code": "AA", "regionLabel": "Aalen", "countryLabel": "Deutschland"}, {"code": "AA", "regionLabel": "Schwäbisch Gmünd", "countryLabel": "Deutschland"}, {"code": "AA", "regionLabel": "Ostalbkreis", "countryLabel": "Deutschland"}, {"code": "AA", "regionLabel": "Neuler", "countryLabel": "Deutschland"}, {"code": "AA", "regionLabel": "Ellwangen", "countryLabel": "Deutschland"}, {"code": "AA", "regionLabel": "Kirchheim am Ries", "countryLabel": "Deutschland"}, {"code": "AA", "regionLabel": "Riesbürg", "countryLabel": "Deutschland"}, {"code": "AA", "regionLabel": "Heubach", "countryLabel": "Deutschland"}, {"code": "AA", "regionLabel": "Tannhausen", "countryLabel": "Deutschland"}, {"code": "AA", "regionLabel": "Abtsgmünd", "countryLabel": "Deutschland"}, {"code": "AA", "regionLabel": "Adelmannsfelden", "countryLabel": "Deutschland"}, {"code": "AA", "regionLabel": "Bartholomä", "countryLabel": "Deutschland"}, {"code": "AA", "regionLabel": "Gschwend", "countryLabel": "Deutschland"}, {"code": "AA", "regionLabel": "Jagstzell", "countryLabel": "Deutschland"}, {"code": "AA", "regionLabel": "Iggingen", "countryLabel": "Deutschland"}, {"code": "AA", "regionLabel": "Unterschneidheim", "countryLabel": "Deutschland"}, {"code": "AA", "regionLabel": "Eschach", "countryLabel": "Deutschland"}, {"code": "AA", "regionLabel": "Göggingen", "countryLabel": "Deutschland"}, {"code": "AA", "regionLabel": "Oberkochen", "countryLabel": "Deutschland"}, {"code": "AA", "regionLabel": "Täferrot", "countryLabel": "Deutschland"}, {"code": "AA", "regionLabel": "Waldstetten", "countryLabel": "Deutschland"}, {"code": "AA", "regionLabel": "Rainau", "countryLabel": "Deutschland"}, {"code": "AA", "regionLabel": "Ruppertshofen", "countryLabel": "Deutschland"}, {"code": "AA", "regionLabel": "Stödtlen", "countryLabel": "Deutschland"}, {"code": "AA", "regionLabel": "Spraitbach", "countryLabel": "Deutschland"}, {"code": "AA", "regionLabel": "Schechingen", "countryLabel": "Deutschland"}, {"code": "AA", "regionLabel": "Wört", "countryLabel": "Deutschland"}, {"code": "AA", "regionLabel": "Rosenberg", "countryLabel": "Deutschland"}, {"code": "AA", "regionLabel": "Neresheim", "countryLabel": "Deutschland"}, {"code": "AA", "regionLabel": "Durlangen", "countryLabel": "Deutschland"}, {"code": "AA", "regionLabel": "Mutlangen", "countryLabel": "Deutschland"}, {"code": "AA", "regionLabel": "Leinzell", "countryLabel": "Deutschland"}, {"code": "AA", "regionLabel": "Lauchheim", "countryLabel": "Deutschland"}, {"code": "AA", "regionLabel": "Hüttlingen", "countryLabel": "Deutschland"}, {"code": "AA", "regionLabel": "Obergröningen", "countryLabel": "Deutschland"}, {"code": "AA", "regionLabel": "Ellenberg", "countryLabel": "Deutschland"}, {"code": "AA", "regionLabel": "Lorch", "countryLabel": "Deutschland"}, {"code": "AA", "regionLabel": "Mögglingen", "countryLabel": "Deutschland"}, {"code": "AA", "regionLabel": "Böbingen an der Rems", "countryLabel": "Deutschland"}, {"code": "AA", "regionLabel": "Bopfingen", "countryLabel": "Deutschland"}, {"code": "AA", "regionLabel": "Westhausen", "countryLabel": "Deutschland"}, {"code": "AA", "regionLabel": "Heuchlingen", "countryLabel": "Deutschland"}, {"code": "AB", "regionLabel": "Aschaffenburg", "countryLabel": "Deutschland"}, {"code": "AB", "regionLabel": "Landkreis Aschaffenburg", "countryLabel": "Deutschland"}, {"code": "AB", "regionLabel": "Kahl am Main", "countryLabel": "Deutschland"}, {"code": "AB", "regionLabel": "Geiselbach", "countryLabel": "Deutschland"}, {"code": "AB", "regionLabel": "Wiesen", "countryLabel": "Deutschland"}, {"code": "AB", "regionLabel": "Bessenbach", "countryLabel": "Deutschland"}, {"code": "AB", "regionLabel": "Hösbach", "countryLabel": "Deutschland"}, {"code": "AB", "regionLabel": "Großostheim", "countryLabel": "Deutschland"}, {"code": "AB", "regionLabel": "Heinrichsthal", "countryLabel": "Deutschland"}, {"code": "AB", "regionLabel": "Stockstadt am Main", "countryLabel": "Deutschland"}, {"code": "AB", "regionLabel": "Heigenbrücken", "countryLabel": "Deutschland"}, {"code": "AB", "regionLabel": "Heimbuchenthal", "countryLabel": "Deutschland"}, {"code": "AB", "regionLabel": "Mainaschaff", "countryLabel": "Deutschland"}, {"code": "AB", "regionLabel": "Dammbach", "countryLabel": "Deutschland"}, {"code": "AB", "regionLabel": "Mömbris", "countryLabel": "Deutschland"}, {"code": "AB", "regionLabel": "Karlstein am Main", "countryLabel": "Deutschland"}, {"code": "AB", "regionLabel": "Blankenbach", "countryLabel": "Deutschland"}, {"code": "AB", "regionLabel": "Glattbach", "countryLabel": "Deutschland"}, {"code": "AB", "regionLabel": "Kleinostheim", "countryLabel": "Deutschland"}, {"code": "AB", "regionLabel": "Westerngrund", "countryLabel": "Deutschland"}, {"code": "AB", "regionLabel": "Kleinkahl", "countryLabel": "Deutschland"}, {"code": "AB", "regionLabel": "Krombach", "countryLabel": "Deutschland"}, {"code": "AB", "regionLabel": "Johannesberg", "countryLabel": "Deutschland"}, {"code": "AB", "regionLabel": "Sailauf", "countryLabel": "Deutschland"}, {"code": "AB", "regionLabel": "Sommerkahl", "countryLabel": "Deutschland"}, {"code": "AB", "regionLabel": "Goldbach", "countryLabel": "Deutschland"}, {"code": "AB", "regionLabel": "Mespelbrunn", "countryLabel": "Deutschland"}, {"code": "AB", "regionLabel": "Schöllkrippen", "countryLabel": "Deutschland"}, {"code": "AB", "regionLabel": "Weibersbrunn", "countryLabel": "Deutschland"}, {"code": "AB", "regionLabel": "Rothenbuch", "countryLabel": "Deutschland"}, {"code": "AB", "regionLabel": "Waldaschaff", "countryLabel": "Deutschland"}, {"code": "AB", "regionLabel": "Laufach", "countryLabel": "Deutschland"}, {"code": "AB", "regionLabel": "Dietersburg", "countryLabel": "Deutschland"}, {"code": "AB", "regionLabel": "Haibach", "countryLabel": "Deutschland"}, {"code": "ABG", "regionLabel": "Landkreis Altenburger Land", "countryLabel": "Deutschland"}, {"code": "ABG", "regionLabel": "Altenburg", "countryLabel": "Deutschland"}, {"code": "ABG", "regionLabel": "Göpfersdorf", "countryLabel": "Deutschland"}, {"code": "ABG", "regionLabel": "Treben", "countryLabel": "Deutschland"}, {"code": "ABG", "regionLabel": "Vollmershain", "countryLabel": "Deutschland"}, {"code": "ABG", "regionLabel": "Posterstein", "countryLabel": "Deutschland"}, {"code": "ABG", "regionLabel": "Jonaswalde", "countryLabel": "Deutschland"}, {"code": "ABG", "regionLabel": "Thonhausen", "countryLabel": "Deutschland"}, {"code": "ABG", "regionLabel": "Wildenbörten", "countryLabel": "Deutschland"}, {"code": "ABG", "regionLabel": "Löbichau", "countryLabel": "Deutschland"}, {"code": "ABG", "regionLabel": "Nöbdenitz", "countryLabel": "Deutschland"}, {"code": "ABG", "regionLabel": "Altkirchen", "countryLabel": "Deutschland"}, {"code": "ABG", "regionLabel": "Lucka", "countryLabel": "Deutschland"}, {"code": "ABG", "regionLabel": "Meuselwitz", "countryLabel": "Deutschland"}, {"code": "ABG", "regionLabel": "Lumpzig", "countryLabel": "Deutschland"}, {"code": "ABG", "regionLabel": "Drogen", "countryLabel": "Deutschland"}, {"code": "ABG", "regionLabel": "Göhren", "countryLabel": "Deutschland"}, {"code": "ABG", "regionLabel": "Dobitschen", "countryLabel": "Deutschland"}, {"code": "ABG", "regionLabel": "Schmölln", "countryLabel": "Deutschland"}, {"code": "ABG", "regionLabel": "Gößnitz", "countryLabel": "Deutschland"}, {"code": "ABG", "regionLabel": "Heukewalde", "countryLabel": "Deutschland"}, {"code": "ABI", "regionLabel": "Landkreis Anhalt-Bitterfeld", "countryLabel": "Deutschland"}, {"code": "ABI", "regionLabel": "Bitterfeld-Wolfen", "countryLabel": "Deutschland"}, {"code": "ABI", "regionLabel": "Zerbst/Anhalt", "countryLabel": "Deutschland"}, {"code": "ABI", "regionLabel": "Zörbig", "countryLabel": "Deutschland"}, {"code": "ABI", "regionLabel": "Aken (Elbe)", "countryLabel": "Deutschland"}, {"code": "ABI", "regionLabel": "Altjeßnitz", "countryLabel": "Deutschland"}, {"code": "ABI", "regionLabel": "Güterglück", "countryLabel": "Deutschland"}, {"code": "ABI", "regionLabel": "Raguhn-Jeßnitz", "countryLabel": "Deutschland"}, {"code": "ABI", "regionLabel": "Südliches Anhalt", "countryLabel": "Deutschland"}, {"code": "ABI", "regionLabel": "Osternienburger Land", "countryLabel": "Deutschland"}, {"code": "ABI", "regionLabel": "Muldestausee", "countryLabel": "Deutschland"}, {"code": "ABI", "regionLabel": "Köthen", "countryLabel": "Deutschland"}, {"code": "ABI", "regionLabel": "Sandersdorf-Brehna", "countryLabel": "Deutschland"}, {"code": "AC", "regionLabel": "Aachen", "countryLabel": "Deutschland"}, {"code": "AC", "regionLabel": "Stolberg", "countryLabel": "Deutschland"}, {"code": "AC", "regionLabel": "Eschweiler", "countryLabel": "Deutschland"}, {"code": "AC", "regionLabel": "Städteregion Aachen", "countryLabel": "Deutschland"}, {"code": "AC", "regionLabel": "Herzogenrath", "countryLabel": "Deutschland"}, {"code": "AC", "regionLabel": "Alsdorf", "countryLabel": "Deutschland"}, {"code": "AC", "regionLabel": "Würselen", "countryLabel": "Deutschland"}, {"code": "AC", "regionLabel": "Roetgen", "countryLabel": "Deutschland"}, {"code": "AC", "regionLabel": "Monschau", "countryLabel": "Deutschland"}, {"code": "AC", "regionLabel": "Simmerath", "countryLabel": "Deutschland"}, {"code": "AC", "regionLabel": "Baesweiler", "countryLabel": "Deutschland"}, {"code": "AC", "regionLabel": "Köpfchen", "countryLabel": "Deutschland"}, {"code": "AC", "regionLabel": "Lemiers", "countryLabel": "Deutschland"}, {"code": "AC", "regionLabel": "Steinebrück", "countryLabel": "Deutschland"}, {"code": "AC", "regionLabel": "Hanbruch", "countryLabel": "Deutschland"}, {"code": "AC", "regionLabel": "Campus Melaten", "countryLabel": "Deutschland"}, {"code": "AC", "regionLabel": "Rehmviertel", "countryLabel": "Deutschland"}, {"code": "AC", "regionLabel": "Viktoriaviertel", "countryLabel": "Deutschland"}, {"code": "AC", "regionLabel": "Steffensviertel", "countryLabel": "Deutschland"}, {"code": "AC", "regionLabel": "Pontviertel", "countryLabel": "Deutschland"}, {"code": "AC", "regionLabel": "Rosviertel", "countryLabel": "Deutschland"}, {"code": "AC", "regionLabel": "Bahnhofsviertel", "countryLabel": "Deutschland"}, {"code": "AC", "regionLabel": "Kronenberg", "countryLabel": "Deutschland"}, {"code": "AC", "regionLabel": "Ronheide", "countryLabel": "Deutschland"}, {"code": "AC", "regionLabel": "Schönforst", "countryLabel": "Deutschland"}, {"code": "AC", "regionLabel": "Lintert", "countryLabel": "Deutschland"}, {"code": "AC", "regionLabel": "Hitfeld", "countryLabel": "Deutschland"}, {"code": "AC", "regionLabel": "Driescher Hof", "countryLabel": "Deutschland"}, {"code": "AC", "regionLabel": "Eich", "countryLabel": "Deutschland"}, {"code": "AC", "regionLabel": "Gut Kullen", "countryLabel": "Deutschland"}, {"code": "AC", "regionLabel": "Steppenberg", "countryLabel": "Deutschland"}, {"code": "AE", "regionLabel": "Vogtlandkreis", "countryLabel": "Deutschland"}, {"code": "AE", "regionLabel": "Eichigt", "countryLabel": "Deutschland"}, {"code": "AE", "regionLabel": "Muldenhammer", "countryLabel": "Deutschland"}, {"code": "AE", "regionLabel": "Rosenbach/Vogtl.", "countryLabel": "Deutschland"}, {"code": "AG", "regionLabel": "Helgoland", "countryLabel": "Deutschland"}, {"code": "AIB", "regionLabel": "Landkreis Rosenheim", "countryLabel": "Deutschland"}, {"code": "AIB", "regionLabel": "Oberschleißheim", "countryLabel": "Deutschland"}, {"code": "AIB", "regionLabel": "Ismaning", "countryLabel": "Deutschland"}, {"code": "AIB", "regionLabel": "Taufkirchen", "countryLabel": "Deutschland"}, {"code": "AIB", "regionLabel": "Neuried", "countryLabel": "Deutschland"}, {"code": "AIB", "regionLabel": "Wasserburg am Inn", "countryLabel": "Deutschland"}, {"code": "AIB", "regionLabel": "Putzbrunn", "countryLabel": "Deutschland"}, {"code": "AIB", "regionLabel": "Garching bei München", "countryLabel": "Deutschland"}, {"code": "AIB", "regionLabel": "Unterföhring", "countryLabel": "Deutschland"}, {"code": "AIB", "regionLabel": "Straßlach-Dingharting", "countryLabel": "Deutschland"}, {"code": "AIB", "regionLabel": "Baierbrunn", "countryLabel": "Deutschland"}, {"code": "AIB", "regionLabel": "Aschheim", "countryLabel": "Deutschland"}, {"code": "AIB", "regionLabel": "Haar", "countryLabel": "Deutschland"}, {"code": "AIB", "regionLabel": "Oberhaching", "countryLabel": "Deutschland"}, {"code": "AIB", "regionLabel": "Schäftlarn", "countryLabel": "Deutschland"}, {"code": "AIB", "regionLabel": "Sauerlach", "countryLabel": "Deutschland"}, {"code": "AIC", "regionLabel": "Landkreis Aichach-Friedberg", "countryLabel": "Deutschland"}, {"code": "AIC", "regionLabel": "Schiltberg", "countryLabel": "Deutschland"}, {"code": "AIC", "regionLabel": "Schmiechen", "countryLabel": "Deutschland"}, {"code": "AIC", "regionLabel": "Sielenbach", "countryLabel": "Deutschland"}, {"code": "AIC", "regionLabel": "Aichach", "countryLabel": "Deutschland"}, {"code": "AIC", "regionLabel": "Pöttmes", "countryLabel": "Deutschland"}, {"code": "AIC", "regionLabel": "Petersdorf", "countryLabel": "Deutschland"}, {"code": "AIC", "regionLabel": "Baar", "countryLabel": "Deutschland"}, {"code": "AIC", "regionLabel": "Kissing", "countryLabel": "Deutschland"}, {"code": "AIC", "regionLabel": "Adelzhausen", "countryLabel": "Deutschland"}, {"code": "AIC", "regionLabel": "Aindling", "countryLabel": "Deutschland"}, {"code": "AIC", "regionLabel": "Inchenhofen", "countryLabel": "Deutschland"}, {"code": "AIC", "regionLabel": "Affing", "countryLabel": "Deutschland"}, {"code": "AIC", "regionLabel": "Todtenweis", "countryLabel": "Deutschland"}, {"code": "AIC", "regionLabel": "Rehling", "countryLabel": "Deutschland"}, {"code": "AIC", "regionLabel": "Mering", "countryLabel": "Deutschland"}, {"code": "AIC", "regionLabel": "Steindorf", "countryLabel": "Deutschland"}, {"code": "AIC", "regionLabel": "Obergriesbach", "countryLabel": "Deutschland"}, {"code": "AIC", "regionLabel": "Hollenbach", "countryLabel": "Deutschland"}, {"code": "AIC", "regionLabel": "Ried", "countryLabel": "Deutschland"}, {"code": "AIC", "regionLabel": "Eurasburg", "countryLabel": "Deutschland"}, {"code": "AIC", "regionLabel": "Dasing", "countryLabel": "Deutschland"}, {"code": "AIC", "regionLabel": "Handzell", "countryLabel": "Deutschland"}, {"code": "AIC", "regionLabel": "Landkreis Aichach", "countryLabel": "Deutschland"}, {"code": "AIC", "regionLabel": "Kühbach", "countryLabel": "Deutschland"}, {"code": "AIC", "regionLabel": "Merching", "countryLabel": "Deutschland"}, {"code": "AK", "regionLabel": "Landkreis Altenkirchen", "countryLabel": "Deutschland"}, {"code": "AK", "regionLabel": "Wissen", "countryLabel": "Deutschland"}, {"code": "AK", "regionLabel": "Mehren", "countryLabel": "Deutschland"}, {"code": "AK", "regionLabel": "Kircheib", "countryLabel": "Deutschland"}, {"code": "AK", "regionLabel": "Ziegenhain", "countryLabel": "Deutschland"}, {"code": "AK", "regionLabel": "Verbandsgemeinde Betzdorf", "countryLabel": "Deutschland"}, {"code": "AK", "regionLabel": "Ölsen", "countryLabel": "Deutschland"}, {"code": "AK", "regionLabel": "Molzhain", "countryLabel": "Deutschland"}, {"code": "AK", "regionLabel": "Fensdorf", "countryLabel": "Deutschland"}, {"code": "AK", "regionLabel": "Oberwambach", "countryLabel": "Deutschland"}, {"code": "AK", "regionLabel": "Altenkirchen", "countryLabel": "Deutschland"}, {"code": "AK", "regionLabel": "Verbandsgemeinde Wissen", "countryLabel": "Deutschland"}, {"code": "AK", "regionLabel": "Oberirsen", "countryLabel": "Deutschland"}, {"code": "AK", "regionLabel": "Rott", "countryLabel": "Deutschland"}, {"code": "AK", "regionLabel": "Herdorf", "countryLabel": "Deutschland"}, {"code": "AK", "regionLabel": "Kirchen", "countryLabel": "Deutschland"}, {"code": "AK", "regionLabel": "Betzdorf", "countryLabel": "Deutschland"}, {"code": "AK", "regionLabel": "Derschen", "countryLabel": "Deutschland"}, {"code": "AK", "regionLabel": "Helmenzen", "countryLabel": "Deutschland"}, {"code": "AK", "regionLabel": "Neitersen", "countryLabel": "Deutschland"}, {"code": "AK", "regionLabel": "Niederfischbach", "countryLabel": "Deutschland"}, {"code": "AK", "regionLabel": "Hirz-Maulsbach", "countryLabel": "Deutschland"}, {"code": "AK", "regionLabel": "Brachbach", "countryLabel": "Deutschland"}, {"code": "AK", "regionLabel": "Weyerbusch", "countryLabel": "Deutschland"}, {"code": "AK", "regionLabel": "Nauroth", "countryLabel": "Deutschland"}, {"code": "AK", "regionLabel": "Niederdreisbach", "countryLabel": "Deutschland"}, {"code": "AK", "regionLabel": "Verbandsgemeinde Altenkirchen (Westerwald)", "countryLabel": "Deutschland"}, {"code": "AK", "regionLabel": "Elkenroth", "countryLabel": "Deutschland"}, {"code": "AK", "regionLabel": "Verbandsgemeinde Flammersfeld", "countryLabel": "Deutschland"}, {"code": "AK", "regionLabel": "Bitzen", "countryLabel": "Deutschland"}, {"code": "AK", "regionLabel": "Hilgenroth", "countryLabel": "Deutschland"}, {"code": "AK", "regionLabel": "Heupelzen", "countryLabel": "Deutschland"}, {"code": "AK", "regionLabel": "Bruchertseifen", "countryLabel": "Deutschland"}, {"code": "AK", "regionLabel": "Mauden", "countryLabel": "Deutschland"}, {"code": "AK", "regionLabel": "Rettersen", "countryLabel": "Deutschland"}, {"code": "AK", "regionLabel": "Racksen", "countryLabel": "Deutschland"}, {"code": "AK", "regionLabel": "Birnbach", "countryLabel": "Deutschland"}, {"code": "AK", "regionLabel": "Weitefeld", "countryLabel": "Deutschland"}, {"code": "AK", "regionLabel": "Helmeroth", "countryLabel": "Deutschland"}, {"code": "AK", "regionLabel": "Hemmelzen", "countryLabel": "Deutschland"}, {"code": "AK", "regionLabel": "Berzhausen", "countryLabel": "Deutschland"}, {"code": "AK", "regionLabel": "Birkenbeul", "countryLabel": "Deutschland"}, {"code": "AK", "regionLabel": "Walterschen", "countryLabel": "Deutschland"}, {"code": "AK", "regionLabel": "Werkhausen", "countryLabel": "Deutschland"}, {"code": "AK", "regionLabel": "Mammelzen", "countryLabel": "Deutschland"}, {"code": "AK", "regionLabel": "Bürdenbach", "countryLabel": "Deutschland"}, {"code": "AK", "regionLabel": "Kraam", "countryLabel": "Deutschland"}, {"code": "AK", "regionLabel": "Eichelhardt", "countryLabel": "Deutschland"}, {"code": "AK", "regionLabel": "Ersfeld", "countryLabel": "Deutschland"}, {"code": "AK", "regionLabel": "Güllesheim", "countryLabel": "Deutschland"}, {"code": "AK", "regionLabel": "Bachenberg", "countryLabel": "Deutschland"}, {"code": "AK", "regionLabel": "Emmerzhausen", "countryLabel": "Deutschland"}, {"code": "AK", "regionLabel": "Niederirsen", "countryLabel": "Deutschland"}, {"code": "AK", "regionLabel": "Kescheid", "countryLabel": "Deutschland"}, {"code": "AK", "regionLabel": "Kettenhausen", "countryLabel": "Deutschland"}, {"code": "AK", "regionLabel": "Etzbach", "countryLabel": "Deutschland"}, {"code": "AK", "regionLabel": "Kausen", "countryLabel": "Deutschland"}, {"code": "AK", "regionLabel": "Eulenberg", "countryLabel": "Deutschland"}, {"code": "AK", "regionLabel": "Busenhausen", "countryLabel": "Deutschland"}, {"code": "AK", "regionLabel": "Elben", "countryLabel": "Deutschland"}, {"code": "AK", "regionLabel": "Breitscheidt", "countryLabel": "Deutschland"}, {"code": "AK", "regionLabel": "Wölmersen", "countryLabel": "Deutschland"}, {"code": "AK", "regionLabel": "Fürthen", "countryLabel": "Deutschland"}, {"code": "AK", "regionLabel": "Fiersbach", "countryLabel": "Deutschland"}, {"code": "AK", "regionLabel": "Fluterschen", "countryLabel": "Deutschland"}, {"code": "AK", "regionLabel": "Berod bei Hachenburg", "countryLabel": "Deutschland"}, {"code": "AK", "regionLabel": "Forstmehren", "countryLabel": "Deutschland"}, {"code": "AK", "regionLabel": "Friedewald", "countryLabel": "Deutschland"}, {"code": "AK", "regionLabel": "Almersbach", "countryLabel": "Deutschland"}, {"code": "AK", "regionLabel": "Dickendorf", "countryLabel": "Deutschland"}, {"code": "AK", "regionLabel": "Hövels", "countryLabel": "Deutschland"}, {"code": "AK", "regionLabel": "Wallmenroth", "countryLabel": "Deutschland"}, {"code": "AK", "regionLabel": "Harbach", "countryLabel": "Deutschland"}, {"code": "AK", "regionLabel": "Birken-Honigsessen", "countryLabel": "Deutschland"}, {"code": "AK", "regionLabel": "Idelberg", "countryLabel": "Deutschland"}, {"code": "AK", "regionLabel": "Ingelbach", "countryLabel": "Deutschland"}, {"code": "AK", "regionLabel": "Isert", "countryLabel": "Deutschland"}, {"code": "AK", "regionLabel": "Flammersfeld", "countryLabel": "Deutschland"}, {"code": "AK", "regionLabel": "Grünebach", "countryLabel": "Deutschland"}, {"code": "AK", "regionLabel": "Volkerzen", "countryLabel": "Deutschland"}, {"code": "AK", "regionLabel": "Daaden", "countryLabel": "Deutschland"}, {"code": "AK", "regionLabel": "Eichen", "countryLabel": "Deutschland"}, {"code": "AK", "regionLabel": "Michelbach", "countryLabel": "Deutschland"}, {"code": "AK", "regionLabel": "Friesenhagen", "countryLabel": "Deutschland"}, {"code": "AK", "regionLabel": "Willroth", "countryLabel": "Deutschland"}, {"code": "AK", "regionLabel": "Mudersbach", "countryLabel": "Deutschland"}, {"code": "AK", "regionLabel": "Gebhardshain", "countryLabel": "Deutschland"}, {"code": "AK", "regionLabel": "Gieleroth", "countryLabel": "Deutschland"}, {"code": "AK", "regionLabel": "Obersteinebach", "countryLabel": "Deutschland"}, {"code": "AK", "regionLabel": "Sörth", "countryLabel": "Deutschland"}, {"code": "AK", "regionLabel": "Burglahr", "countryLabel": "Deutschland"}, {"code": "AK", "regionLabel": "Schutzbach", "countryLabel": "Deutschland"}, {"code": "AK", "regionLabel": "Oberlahr", "countryLabel": "Deutschland"}, {"code": "AK", "regionLabel": "Orfgen", "countryLabel": "Deutschland"}, {"code": "AK", "regionLabel": "Reiferscheid", "countryLabel": "Deutschland"}, {"code": "AK", "regionLabel": "Malberg", "countryLabel": "Deutschland"}, {"code": "AK", "regionLabel": "Niedersteinebach", "countryLabel": "Deutschland"}, {"code": "AK", "regionLabel": "Seifen", "countryLabel": "Deutschland"}, {"code": "AK", "regionLabel": "Nisterberg", "countryLabel": "Deutschland"}, {"code": "AK", "regionLabel": "Giershausen", "countryLabel": "Deutschland"}, {"code": "AK", "regionLabel": "Seelbach bei Hamm", "countryLabel": "Deutschland"}, {"code": "AK", "regionLabel": "Steineroth", "countryLabel": "Deutschland"}, {"code": "AK", "regionLabel": "Stürzelbach", "countryLabel": "Deutschland"}, {"code": "AK", "regionLabel": "Obernau", "countryLabel": "Deutschland"}, {"code": "AK", "regionLabel": "Pleckhausen", "countryLabel": "Deutschland"}, {"code": "AK", "regionLabel": "Forst", "countryLabel": "Deutschland"}, {"code": "AK", "regionLabel": "Mittelhof", "countryLabel": "Deutschland"}, {"code": "AK", "regionLabel": "Scheuerfeld", "countryLabel": "Deutschland"}, {"code": "AK", "regionLabel": "Horhausen", "countryLabel": "Deutschland"}, {"code": "AK", "regionLabel": "Katzwinkel", "countryLabel": "Deutschland"}, {"code": "AK", "regionLabel": "Hamm (Sieg)", "countryLabel": "Deutschland"}, {"code": "AK", "regionLabel": "Alsdorf", "countryLabel": "Deutschland"}, {"code": "AK", "regionLabel": "Krunkel", "countryLabel": "Deutschland"}, {"code": "AK", "regionLabel": "Pracht", "countryLabel": "Deutschland"}, {"code": "AK", "regionLabel": "Schürdt", "countryLabel": "Deutschland"}, {"code": "AK", "regionLabel": "Seelbach", "countryLabel": "Deutschland"}, {"code": "AK", "regionLabel": "Rosenheim", "countryLabel": "Deutschland"}, {"code": "AK", "regionLabel": "Hasselbach", "countryLabel": "Deutschland"}, {"code": "AK", "regionLabel": "Schöneberg", "countryLabel": "Deutschland"}, {"code": "AK", "regionLabel": "Selbach", "countryLabel": "Deutschland"}, {"code": "AK", "regionLabel": "Roth", "countryLabel": "Deutschland"}, {"code": "AK", "regionLabel": "Obererbach", "countryLabel": "Deutschland"}, {"code": "AK", "regionLabel": "Peterslahr", "countryLabel": "Deutschland"}, {"code": "AK", "regionLabel": "Steinebach/Sieg", "countryLabel": "Deutschland"}]